appimage_updater/__init__.py
appimage_updater/__main__.py
appimage_updater/_version.py
appimage_updater/main.py
appimage_updater/py.typed
appimage_updater/cli/__init__.py
appimage_updater/cli/application.py
appimage_updater/cli/options.py
appimage_updater/cli/handlers/__init__.py
appimage_updater/cli/handlers/add_handler.py
appimage_updater/cli/handlers/base.py
appimage_updater/cli/handlers/check_handler.py
appimage_updater/cli/handlers/config_handler.py
appimage_updater/cli/handlers/edit_handler.py
appimage_updater/cli/handlers/fix_handler.py
appimage_updater/cli/handlers/list_handler.py
appimage_updater/cli/handlers/remove_handler.py
appimage_updater/cli/handlers/repository_handler.py
appimage_updater/cli/handlers/show_handler.py
appimage_updater/commands/__init__.py
appimage_updater/commands/add_command.py
appimage_updater/commands/base.py
appimage_updater/commands/base_command.py
appimage_updater/commands/check_command.py
appimage_updater/commands/config_command.py
appimage_updater/commands/edit_command.py
appimage_updater/commands/factory.py
appimage_updater/commands/fix_command.py
appimage_updater/commands/list_command.py
appimage_updater/commands/mixins.py
appimage_updater/commands/parameters.py
appimage_updater/commands/remove_command.py
appimage_updater/commands/repository_command.py
appimage_updater/commands/show_command.py
appimage_updater/config/__init__.py
appimage_updater/config/command.py
appimage_updater/config/loader.py
appimage_updater/config/manager.py
appimage_updater/config/models.py
appimage_updater/config/operations.py
appimage_updater/config/cmd/__init__.py
appimage_updater/config/cmd/display_utilities.py
appimage_updater/config/cmd/error_handling.py
appimage_updater/config/cmd/file_operations.py
appimage_updater/config/cmd/setting_operations.py
appimage_updater/core/__init__.py
appimage_updater/core/distribution_selector.py
appimage_updater/core/downloader.py
appimage_updater/core/http_service.py
appimage_updater/core/http_trace.py
appimage_updater-0.6.0.dist-info/METADATA
appimage_updater-0.6.0.dist-info/WHEEL
appimage_updater-0.6.0.dist-info/entry_points.txt
appimage_updater-0.6.0.dist-info/licenses/LICENSE
appimage_updater-0.6.0.dist-info/RECORD
