Metadata-Version: 2.4
Name: appimage-updater
Version: 0.6.0
Summary: A Linux service for automating finding and downloading AppImage applications
Project-URL: Homepage, https://github.com/royw/appimage-updater
Project-URL: Documentation, https://royw.github.io/appimage-updater/
Project-URL: Repository, https://github.com/royw/appimage-updater
Project-URL: Issues, https://github.com/royw/appimage-updater/issues
Project-URL: Changelog, https://github.com/royw/appimage-updater/blob/main/CHANGELOG.md
Author-email: Roy Wright <roy@wright.org>
License-Expression: MIT
License-File: LICENSE
Keywords: appimage,automation,linux,package-manager,updater
Classifier: Development Status :: 4 - Beta
Classifier: Environment :: Console
Classifier: Intended Audience :: Developers
Classifier: Intended Audience :: End Users/Desktop
Classifier: Intended Audience :: System Administrators
Classifier: License :: OSI Approved :: MIT License
Classifier: Operating System :: POSIX :: Linux
Classifier: Programming Language :: Python :: 3
Classifier: Programming Language :: Python :: 3.11
Classifier: Programming Language :: Python :: 3.12
Classifier: Programming Language :: Python :: 3.13
Classifier: Topic :: System :: Archiving :: Packaging
Classifier: Topic :: System :: Software Distribution
Classifier: Topic :: Utilities
Requires-Python: >=3.11
Requires-Dist: httpx>=0.25.0
Requires-Dist: importlib-metadata>=8.7.0
Requires-Dist: loguru>=0.7.0
Requires-Dist: packaging>=23.0
Requires-Dist: pydantic>=2.5.0
Requires-Dist: rich>=13.0.0
Requires-Dist: typer>=0.9.0
